fileglancer/__init__.py
fileglancer/_version.py
fileglancer/alembic.ini
fileglancer/app.py
fileglancer/auth.py
fileglancer/cli.py
fileglancer/database.py
fileglancer/dev_launch.py
fileglancer/filestore.py
fileglancer/issues.py
fileglancer/log.py
fileglancer/model.py
fileglancer/settings.py
fileglancer/stamp_db.py
fileglancer/user_context.py
fileglancer/utils.py
fileglancer/alembic/env.py
fileglancer/alembic/script.py.mako
fileglancer/alembic/versions/1fb113ca1847_add_sessions_table.py
fileglancer/alembic/versions/2d1f0e6b8c91_add_neuroglancer_states_table.py
fileglancer/alembic/versions/4bd357f37922_add_external_buckets_table.py
fileglancer/alembic/versions/711feaa741bb_add_table_name_column_to_lastrefreshdb.py
fileglancer/alembic/versions/9783bd3941f1_initial_schema.py
fileglancer/alembic/versions/9812335c52b6_add_session_secret_key_hash_to_sessions.py
fileglancer/ui/index.html
fileglancer/ui/logo.svg
fileglancer/ui/assets/aics_website-3d-cell-viewer-Bq_ulvph.png
fileglancer/ui/assets/blosc-CCttI16P.js
fileglancer/ui/assets/blosc-CCttI16P.js.map
fileglancer/ui/assets/chunk-INHXZS53-COD47_NQ.js
fileglancer/ui/assets/chunk-INHXZS53-COD47_NQ.js.map
fileglancer/ui/assets/error_icon_gradient-cjdu_ZfI.png
fileglancer/ui/assets/lz4-CmGaR9_W.js
fileglancer/ui/assets/lz4-CmGaR9_W.js.map
fileglancer/ui/assets/main-BnhHhsrA.css
fileglancer/ui/assets/main-_Te0PB39.js
fileglancer/ui/assets/main-_Te0PB39.js.map
fileglancer/ui/assets/neuroglancer-Bx6J9FBK.png
fileglancer/ui/assets/vizarr_logo-DDTblXww.png
fileglancer/ui/assets/zarr-BY8VMHUY.jpg
fileglancer/ui/assets/zstd-iGpO0Hdm.js
fileglancer/ui/assets/zstd-iGpO0Hdm.js.map
fileglancer-2.4.0.dist-info/METADATA
fileglancer-2.4.0.dist-info/WHEEL
fileglancer-2.4.0.dist-info/entry_points.txt
fileglancer-2.4.0.dist-info/licenses/LICENSE
fileglancer-2.4.0.dist-info/RECORD
