Metadata-Version: 2.4
Name: fileglancer
Version: 2.4.0
Summary: Browse, share, and publish files on the Janelia file system
Project-URL: Homepage, https://github.com/JaneliaSciComp/fileglancer
Project-URL: Bug Tracker, https://github.com/JaneliaSciComp/fileglancer/issues
Project-URL: Repository, https://github.com/JaneliaSciComp/fileglancer.git
Author-email: Allison Truhlar <truhlara@janelia.hhmi.org>, Jody Clements <clementsj@janelia.hhmi.org>, Cristian Goina <goinac@janelia.hhmi.org>, Konrad Rokicki <rokickik@janelia.hhmi.org>
License: BSD 3-Clause License
License-File: LICENSE
Keywords: file browser,ngff,scientific imaging
Classifier: License :: OSI Approved :: BSD License
Classifier: Programming Language :: Python
Classifier: Programming Language :: Python :: 3
Classifier: Programming Language :: Python :: 3.10
Classifier: Programming Language :: Python :: 3.11
Classifier: Programming Language :: Python :: 3.12
Classifier: Programming Language :: Python :: 3.13
Requires-Python: <4,>=3.14.0
Requires-Dist: aiosqlite>=0.21.0
Requires-Dist: alembic>=1.17.0
Requires-Dist: atlassian-python-api>=4.0.7
Requires-Dist: authlib>=1.6.5
Requires-Dist: cachetools>=6.2.1
Requires-Dist: click>=8.0
Requires-Dist: cryptography>=41.0.0
Requires-Dist: fastapi>=0.119.1
Requires-Dist: httpx>=0.28
Requires-Dist: itsdangerous>=2.2.0
Requires-Dist: loguru>=0.7.3
Requires-Dist: lxml>=5.3.1
Requires-Dist: pandas>=2.3.3
Requires-Dist: psycopg2-binary<3,>=2.9.10
Requires-Dist: pydantic-settings>=2.11.0
Requires-Dist: pydantic>=2.10.6
Requires-Dist: python-jose<4,>=3.5.0
Requires-Dist: sqlalchemy>=2.0.44
Requires-Dist: uvicorn>=0.38.0
Requires-Dist: x2s3>=1.1.0
Provides-Extra: release
Requires-Dist: hatch; extra == 'release'
Requires-Dist: twine; extra == 'release'
Provides-Extra: test
Requires-Dist: coverage; extra == 'test'
Requires-Dist: httpx>=0.28; extra == 'test'
Requires-Dist: pytest; extra == 'test'
Requires-Dist: pytest-asyncio; extra == 'test'
Requires-Dist: pytest-cov; extra == 'test'
Requires-Dist: pytest-html; extra == 'test'
Requires-Dist: requests-mock; extra == 'test'
